[
  {
    "title": "Major exchange lists new token; price surges",
    "url": "https://example.com/sample-a",
    "source": "CoinDesk",
    "published_at": "2024-01-01T09:00:00Z",
    "category": "crypto"
  },
  {
    "title": "Protocol exploit triggers panic and liquidation",
    "url": "https://example.com/sample-b",
    "source": "CoinTelegraph",
    "published_at": "2024-01-01T08:30:00Z",
    "category": "crypto"
  },
  {
    "title": "Global markets mixed as rates expectations shift",
    "url": "https://example.com/sample-c",
    "source": "Reuters Markets",
    "published_at": "2024-01-01T08:00:00Z",
    "category": "global"
  }
] 